{"Commercial_NetPosition_change": {"model_name": "extra", "params": {"n_estimators": 600, "max_depth": 11, "min_samples_leaf": 1, "max_features": "sqrt"}}, "CommercialLongPosition_change": {"model_name": "rf", "params": {"n_estimators": 1200, "max_depth": 20, "min_samples_leaf": 3, "max_features": "sqrt"}}, "CommercialShortPosition_change": {"model_name": "rf", "params": {"n_estimators": 1000, "max_depth": 25, "min_samples_leaf": 1, "max_features": "sqrt"}}, "Commercial_NetPosition_to_openinterest_change": {"model_name": "ols", "params": {}}, "CommercialLongPosition_to_openinterest_change": {"model_name": "rf", "params": {"n_estimators": 600, "max_depth": 27, "min_samples_leaf": 8, "max_features": "log2"}}, "CommercialShortPosition_to_openinterest_change": {"model_name": "rf", "params": {"n_estimators": 200, "max_depth": 30, "min_samples_leaf": 1, "max_features": "log2"}}}